LICENSE
MANIFEST.in
README.md
runtests.py
setup.py
dj_timelinejs.egg-info/PKG-INFO
dj_timelinejs.egg-info/SOURCES.txt
dj_timelinejs.egg-info/dependency_links.txt
dj_timelinejs.egg-info/top_level.txt
timelinejs/__init__.py
timelinejs/admin.py
timelinejs/forms.py
timelinejs/models.py
timelinejs/tests.py
timelinejs/urls.py
timelinejs/utils.py
timelinejs/views.py
timelinejs/static/css/loading.gif
timelinejs/static/css/timeline.css
timelinejs/static/css/timeline.png
timelinejs/static/css/timeline@2x.png
timelinejs/static/css/themes/dark.css
timelinejs/static/css/themes/timeline-dark.png
timelinejs/static/css/themes/timeline-dark@2x.png
timelinejs/static/css/themes/timeline-texture.png
timelinejs/static/css/themes/font/AbrilFatface-Average.css
timelinejs/static/css/themes/font/Arvo-PTSans.css
timelinejs/static/css/themes/font/Bevan-PotanoSans.css
timelinejs/static/css/themes/font/BreeSerif-OpenSans.css
timelinejs/static/css/themes/font/DroidSerif-DroidSans.css
timelinejs/static/css/themes/font/Georgia-Helvetica.css
timelinejs/static/css/themes/font/Lekton-Molengo.css
timelinejs/static/css/themes/font/Lora-Istok.css
timelinejs/static/css/themes/font/Merriweather-NewsCycle.css
timelinejs/static/css/themes/font/NewsCycle-Merriweather.css
timelinejs/static/css/themes/font/NixieOne-Ledger.css
timelinejs/static/css/themes/font/PT.css
timelinejs/static/css/themes/font/PTSerif-PTSans.css
timelinejs/static/css/themes/font/Pacifico-Arimo.css
timelinejs/static/css/themes/font/PlayfairDisplay-Muli.css
timelinejs/static/css/themes/font/PoiretOne-Molengo.css
timelinejs/static/css/themes/font/Rancho-Gudea.css
timelinejs/static/css/themes/font/SansitaOne-Kameron.css
timelinejs/static/js/storyjs-embed.js
timelinejs/static/js/timeline-min.js
timelinejs/static/js/timeline.js
timelinejs/static/js/locale/af.js
timelinejs/static/js/locale/ar.js
timelinejs/static/js/locale/bg.js
timelinejs/static/js/locale/ca.js
timelinejs/static/js/locale/cz.js
timelinejs/static/js/locale/da.js
timelinejs/static/js/locale/de.js
timelinejs/static/js/locale/el.js
timelinejs/static/js/locale/en.js
timelinejs/static/js/locale/es.js
