Metadata-Version: 1.0
Name: dj-timelinejs
Version: 0.1.2
Summary: Support for serving TimelineJS from Django sites.
Home-page: https://github.com/azundo/dj-timelinejs/
Author: Ben Best
Author-email: ben.best@gmail.com,
License: BSD license and MPL 2.0, see LICENSE
Platform: UNKNOWN
